CHANGES.rst
DESCRIPTION.rst
LICENSE
MANIFEST.in
README.md
setup.py
src/wai.annotations.indexedpng.egg-info/PKG-INFO
src/wai.annotations.indexedpng.egg-info/SOURCES.txt
src/wai.annotations.indexedpng.egg-info/dependency_links.txt
src/wai.annotations.indexedpng.egg-info/entry_points.txt
src/wai.annotations.indexedpng.egg-info/namespace_packages.txt
src/wai.annotations.indexedpng.egg-info/requires.txt
src/wai.annotations.indexedpng.egg-info/top_level.txt
src/wai/annotations/indexed_png/__init__.py
src/wai/annotations/indexed_png/component/_FromIndexedPNG.py
src/wai/annotations/indexed_png/component/_IndexedPNGReader.py
src/wai/annotations/indexed_png/component/_IndexedPNGWriter.py
src/wai/annotations/indexed_png/component/_ToIndexedPNG.py
src/wai/annotations/indexed_png/component/__init__.py
src/wai/annotations/indexed_png/specifier/_IndexedPNGInputFormatSpecifier.py
src/wai/annotations/indexed_png/specifier/_IndexedPNGOutputFormatSpecifier.py
src/wai/annotations/indexed_png/specifier/__init__.py
src/wai/annotations/indexed_png/util/__init__.py
src/wai/annotations/indexed_png/util/_format.py